ccs_digitalmarketplace_content_loader-13.16.0.dist-info/licenses/LICENCE
dmcontent/__init__.py
dmcontent/content_loader.py
dmcontent/converters.py
dmcontent/errors.py
dmcontent/formats.py
dmcontent/govuk_frontend.py
dmcontent/html.py
dmcontent/markdown.py
dmcontent/messages.py
dmcontent/metadata.py
dmcontent/py.typed
dmcontent/questions.py
dmcontent/utils.py
ccs_digitalmarketplace_content_loader-13.16.0.dist-info/METADATA
ccs_digitalmarketplace_content_loader-13.16.0.dist-info/WHEEL
ccs_digitalmarketplace_content_loader-13.16.0.dist-info/top_level.txt
ccs_digitalmarketplace_content_loader-13.16.0.dist-info/RECORD
