Metadata-Version: 2.4
Name: ccs-digitalmarketplace-content-loader
Version: 13.16.0
Summary: Digital Marketplace Content Loader
Author: GDS Developers, CCS Developers
Project-URL: Homepage, https://github.com/Crown-Commercial-Service/ccs-digitalmarketplace-content-loader
Project-URL: Repository, https://github.com/Crown-Commercial-Service/ccs-digitalmarketplace-content-loader.git
Project-URL: Issues, https://github.com/Crown-Commercial-Service/ccs-digitalmarketplace-content-loader/issues
Project-URL: Changelog, https://github.com/Crown-Commercial-Service/ccs-digitalmarketplace-content-loader/CHANGELOG.md
Requires-Python: <3.15,>=3.11
License-File: LICENCE
Requires-Dist: Flask<3.2,>=3.0
Requires-Dist: Markdown<4.0.0,>=3.0.0
Requires-Dist: PyYAML<7.0,>=5.1.2
Requires-Dist: inflection<1.0.0,>=0.3.1
Requires-Dist: ccs-digitalmarketplace-utils>=79.8.0
Provides-Extra: dev
Requires-Dist: flake8==7.3.0; extra == "dev"
Requires-Dist: mypy==1.19.1; extra == "dev"
Requires-Dist: types-Markdown; extra == "dev"
Requires-Dist: types-PyYAML; extra == "dev"
Requires-Dist: pytest==9.0.2; extra == "dev"
Requires-Dist: pytest-cov==7.0.0; extra == "dev"
Requires-Dist: syrupy==5.0.0; extra == "dev"
Requires-Dist: pre-commit==4.5.1; extra == "dev"
Dynamic: license-file
